{
  "project_info": {
    "project_number": "796618306938",
    "project_id": "lab3-3ee4e",
    "storage_bucket": "lab3-3ee4e.firebasestorage.app"
  },
  "client": [
    {
      "client_info": {
        "mobilesdk_app_id": "1:796618306938:android:9e4c646db228feeff312c3",
        "android_client_info": {
          "package_name": "com.example.lab2"
        }
      },
      "oauth_client": [],
      "api_key": [
        {
          "current_key": "AIzaSyD5SDbPvHsVRDiOO2Wt9twCVDVgV8D6Fv4"
        }
      ],
      "services": {
        "appinvite_service": {
          "other_platform_oauth_client": []
        }
      }
    }
  ],
  "configuration_version": "1"
}